sports/__init__.py
sports/constants.py
sports/decorators.py
sports/fb/__init__.py
sports/fb/constants.py
sports/fb/fb_utils.py
sports/fb/league_ids.py
sports/fb/roster.py
sports/fb/schedule.py
sports/fb/squad_ids.py
sports/fb/team.py
sports/mlb/__init__.py
sports/mlb/boxscore.py
sports/mlb/constants.py
sports/mlb/mlb_utils.py
sports/mlb/player.py
sports/mlb/roster.py
sports/mlb/schedule.py
sports/mlb/teams.py
sports/nba/__init__.py
sports/nba/boxscore.py
sports/nba/constants.py
sports/nba/nba_utils.py
sports/nba/player.py
sports/nba/roster.py
sports/nba/schedule.py
sports/nba/teams.py
sports/ncaab/__init__.py
sports/ncaab/boxscore.py
sports/ncaab/conferences.py
sports/ncaab/constants.py
sports/ncaab/ncaab_utils.py
sports/ncaab/player.py
sports/ncaab/rankings.py
sports/ncaab/roster.py
sports/ncaab/schedule.py
sports/ncaab/teams.py
sports/ncaaf/__init__.py
sports/ncaaf/boxscore.py
sports/ncaaf/conferences.py
sports/ncaaf/constants.py
sports/ncaaf/ncaaf_utils.py
sports/ncaaf/player.py
sports/ncaaf/rankings.py
sports/ncaaf/roster.py
sports/ncaaf/schedule.py
sports/ncaaf/teams.py
sports/nfl/__init__.py
sports/nfl/boxscore.py
sports/nfl/constants.py
sports/nfl/nfl_utils.py
sports/nfl/player.py
sports/nfl/roster.py
sports/nfl/schedule.py
sports/nfl/teams.py
sports/nhl/__init__.py
sports/nhl/boxscore.py
sports/nhl/constants.py
sports/nhl/nhl_utils.py
sports/nhl/player.py
sports/nhl/roster.py
sports/nhl/schedule.py
sports/nhl/teams.py
sports/utils.py
pysports_stats-0.2.1.dist-info/LICENSE
pysports_stats-0.2.1.dist-info/WHEEL
pysports_stats-0.2.1.dist-info/METADATA
pysports_stats-0.2.1.dist-info/RECORD
