Metadata-Version: 2.1
Name: pysports-stats
Version: 0.2.1
Summary: A free sports API written for python
License: MIT
Author: Brandon Veber
Requires-Python: >=3.8,<4.0
Classifier: License :: OSI Approved :: MIT License
Classifier: Operating System :: POSIX :: Linux
Classifier: Programming Language :: Python :: 3
Classifier: Programming Language :: Python :: 3.8
Classifier: Programming Language :: Python :: 3.9
Classifier: Programming Language :: Python :: 3.10
Classifier: Programming Language :: Python :: 3.11
Classifier: Programming Language :: Python :: 3.8
Classifier: Programming Language :: Python :: 3.9
Requires-Dist: numpy (>=1.21.3,<2.0.0)
Requires-Dist: pandas (>=0.24.1)
Requires-Dist: pyquery (>=1.4.0)
Requires-Dist: requests (>=2.18.4)
